raspberry_py/__init__.py
raspberry_py/gpio/__init__.py
raspberry_py/gpio/adc.py
raspberry_py/gpio/controls.py
raspberry_py/gpio/displays.py
raspberry_py/gpio/examples/__init__.py
raspberry_py/gpio/examples/adc.py
raspberry_py/gpio/examples/adc_multicolored_led.py
raspberry_py/gpio/examples/alarming_led_bar_with_button.py
raspberry_py/gpio/examples/attitude.py
raspberry_py/gpio/examples/blinking_led.py
raspberry_py/gpio/examples/blinking_led_with_button.py
raspberry_py/gpio/examples/blinking_led_with_clock.py
raspberry_py/gpio/examples/breathing_led.py
raspberry_py/gpio/examples/buzzer_with_button.py
raspberry_py/gpio/examples/buzzing_led_bar_with_button.py
raspberry_py/gpio/examples/dc_motor_with_button_relay.py
raspberry_py/gpio/examples/dc_motor_with_gpio_relay.py
raspberry_py/gpio/examples/dc_motor_with_potentiometer.py
raspberry_py/gpio/examples/freenove_smart_car.py
raspberry_py/gpio/examples/hw_pwm_direct_drive.py
raspberry_py/gpio/examples/hw_pwm_indirect_drive.py
raspberry_py/gpio/examples/hygrothermograph.py
raspberry_py/gpio/examples/hygrothermograph_with_lcd.py
raspberry_py/gpio/examples/infrared_motion_sensor.py
raspberry_py/gpio/examples/joystick.py
raspberry_py/gpio/examples/lcd.py
raspberry_py/gpio/examples/led_bar.py
raspberry_py/gpio/examples/led_bar_with_button.py
raspberry_py/gpio/examples/led_matrix.py
raspberry_py/gpio/examples/limit_switch.py
raspberry_py/gpio/examples/matrix_keypad.py
raspberry_py/gpio/examples/multicolored_led.py
raspberry_py/gpio/examples/photoresistor.py
raspberry_py/gpio/examples/raspberry_py_elevator/__init__.py
raspberry_py/gpio/examples/raspberry_py_elevator/assemble.py
raspberry_py/gpio/examples/raspberry_py_elevator/move_up_and_down.py
raspberry_py/gpio/examples/rotary_encoder.py
raspberry_py/gpio/examples/rotary_encoder_dual_multiprocess.py
raspberry_py/gpio/examples/rotary_encoder_multiprocess.py
raspberry_py/gpio/examples/rotary_encoder_multiprocess_two_signal_accuracy_test.py
raspberry_py-0.6.0.dist-info/LICENSE
raspberry_py-0.6.0.dist-info/METADATA
raspberry_py-0.6.0.dist-info/WHEEL
raspberry_py-0.6.0.dist-info/entry_points.txt
raspberry_py-0.6.0.dist-info/RECORD
