Metadata-Version: 2.1
Name: raspberry-py
Version: 0.6.0
Summary: A Python/REST interface for GPIO circuits running on the Raspberry Pi
Home-page: https://github.com/MatthewGerber/raspberry-py
Author: Matthew Gerber
Author-email: gerber.matthew@gmail.com
Requires-Python: >=3.10
Classifier: Programming Language :: Python :: 3
Classifier: Programming Language :: Python :: 3.10
Classifier: Programming Language :: Python :: 3.11
Classifier: Programming Language :: Python :: 3.12
Requires-Dist: Flask (>=3.0,<4.0)
Requires-Dist: Flask-Cors (>=4.0,<5.0)
Requires-Dist: RPi.GPIO (>=0.7,<1.0)
Requires-Dist: numpy (>=1.26,<2.0)
Requires-Dist: opencv-python (>=4.8,<5.0)
Requires-Dist: rpi-ws281x (>=5.0,<6.0)
Requires-Dist: smbus2 (>=0.4,<1.0)
Project-URL: Repository, https://github.com/MatthewGerber/raspberry-py
